bark_detection/__init__.py
bark_detection/bark_detection.py
bark_detection/model/__init__.py
bark_detection/model/model.h5
bark_detection/model/model.json
bark_detection-0.1.2.dist-info/METADATA
bark_detection-0.1.2.dist-info/WHEEL
bark_detection-0.1.2.dist-info/top_level.txt
bark_detection-0.1.2.dist-info/RECORD
