Metadata-Version: 2.1
Name: bark_detection
Version: 0.1.2
Summary: Package for bark detection in audio file
Author: jgab
Keywords: python,ML,bark,detection
Classifier: Development Status :: 1 - Planning
Classifier: Programming Language :: Python :: 3
Requires-Dist: librosa (==0.10.1)
Requires-Dist: tensorflow (==2.13.0)
Requires-Dist: matplotlib (==3.7.2)
Requires-Dist: pandas (==2.1.1)
Requires-Dist: numpy (==1.24.3)
Requires-Dist: tensorflow-io-gcs-filesystem (==0.34.0)
